{"project":{"name":"akkount","namespace":"","locales":[{"code":"en","language":"English","dataFormats":{}}]},"entities":[{"name":"akk_Account","className":"Account","packageName":"akkount.entity","dataStore":"main","table":"AKK_ACCOUNT","embeddable":false,"persistentEntity":true,"replaceParent":false,"systemLevel":false,"namePattern":"%s|name","mappedSuperclass":false,"fqn":"akkount.entity.Account","parentPackage":"com.haulmont.cuba.core.entity","parentClassName":"StandardEntity","idAttributeName":"id","attributes":[{"name":"name","type":{"packageName":"java.lang","className":"String","fqn":"java.lang.String","label":"String"},"mappingType":"DATATYPE","readOnly":false,"column":"NAME","mandatory":true,"unique":true,"length":"20","transient":false},{"name":"description","type":{"packageName":"java.lang","className":"String","fqn":"java.lang.String","label":"String"},"mappingType":"DATATYPE","readOnly":false,"column":"DESCRIPTION","mandatory":false,"unique":false,"length":"100","transient":false},{"name":"currency","type":{"packageName":"akkount.entity","className":"Currency","fqn":"akkount.entity.Currency","label":"Currency","entityName":"akk_Currency"},"mappingType":"ASSOCIATION","cardinality":"MANY_TO_ONE","readOnly":false,"column":"CURRENCY_ID","mandatory":true,"unique":false,"length":"255","transient":false},{"name":"currencyCode","type":{"packageName":"java.lang","className":"String","fqn":"java.lang.String","label":"String"},"mappingType":"DATATYPE","readOnly":false,"column":"CURRENCY_CODE","mandatory":true,"unique":false,"length":"3","transient":false},{"name":"active","type":{"packageName":"java.lang","className":"Boolean","fqn":"java.lang.Boolean","label":"Boolean"},"mappingType":"DATATYPE","readOnly":false,"column":"ACTIVE","mandatory":false,"unique":false,"length":"255","transient":false},{"name":"group","type":{"packageName":"java.lang","className":"Integer","fqn":"java.lang.Integer","label":"Integer"},"mappingType":"DATATYPE","readOnly":false,"column":"GROUP_","mandatory":false,"unique":false,"length":"255","transient":false}]},{"name":"akk_Balance","className":"Balance","packageName":"akkount.entity","dataStore":"main","table":"AKK_BALANCE","embeddable":false,"persistentEntity":true,"replaceParent":false,"systemLevel":false,"mappedSuperclass":false,"fqn":"akkount.entity.Balance","parentPackage":"com.haulmont.cuba.core.entity","parentClassName":"StandardEntity","idAttributeName":"id","attributes":[{"name":"balanceDate","type":{"packageName":"java.util","className":"Date","fqn":"java.util.Date","label":"Date"},"mappingType":"DATATYPE","readOnly":false,"column":"BALANCE_DATE","mandatory":true,"unique":false,"length":"255","transient":false,"temporalType":"DATE"},{"name":"account","type":{"packageName":"akkount.entity","className":"Account","fqn":"akkount.entity.Account","label":"Account","entityName":"akk_Account"},"mappingType":"ASSOCIATION","cardinality":"MANY_TO_ONE","readOnly":false,"column":"ACCOUNT_ID","mandatory":true,"unique":false,"length":"255","transient":false},{"name":"amount","type":{"packageName":"java.math","className":"BigDecimal","fqn":"java.math.BigDecimal","label":"BigDecimal"},"mappingType":"DATATYPE","readOnly":false,"column":"AMOUNT","mandatory":false,"unique":false,"length":"255","transient":false}]},{"name":"akk_Category","className":"Category","packageName":"akkount.entity","dataStore":"main","table":"AKK_CATEGORY","embeddable":false,"persistentEntity":true,"replaceParent":false,"systemLevel":false,"namePattern":"%s|name","mappedSuperclass":false,"fqn":"akkount.entity.Category","parentPackage":"com.haulmont.cuba.core.entity","parentClassName":"StandardEntity","idAttributeName":"id","attributes":[{"name":"name","type":{"packageName":"java.lang","className":"String","fqn":"java.lang.String","label":"String"},"mappingType":"DATATYPE","readOnly":false,"column":"NAME","mandatory":true,"unique":false,"length":"50","transient":false},{"name":"description","type":{"packageName":"java.lang","className":"String","fqn":"java.lang.String","label":"String"},"mappingType":"DATATYPE","readOnly":false,"column":"DESCRIPTION","mandatory":false,"unique":false,"length":"100","transient":false},{"name":"catType","type":{"packageName":"akkount.entity","className":"CategoryType","fqn":"akkount.entity.CategoryType","label":"CategoryType"},"mappingType":"ENUM","readOnly":false,"column":"CAT_TYPE","mandatory":true,"unique":false,"length":"255","transient":false}]},{"name":"akk_CategoryBalance","className":"CategoryAmount","packageName":"akkount.entity","dataStore":"main","embeddable":false,"persistentEntity":false,"replaceParent":false,"systemLevel":false,"mappedSuperclass":false,"fqn":"akkount.entity.CategoryAmount","parentPackage":"com.haulmont.cuba.core.entity","parentClassName":"BaseUuidEntity","idAttributeName":"id","attributes":[{"name":"category","type":{"packageName":"akkount.entity","className":"Category","fqn":"akkount.entity.Category","label":"Category","entityName":"akk_Category"},"mappingType":"ASSOCIATION","cardinality":"ONE_TO_ONE","readOnly":false,"mandatory":false,"unique":false,"length":"255","transient":false},{"name":"amount","type":{"packageName":"java.math","className":"BigDecimal","fqn":"java.math.BigDecimal","label":"BigDecimal"},"mappingType":"DATATYPE","readOnly":false,"column":"amount","mandatory":false,"unique":false,"length":"255","transient":false}]},{"name":"akk_Currency","className":"Currency","packageName":"akkount.entity","dataStore":"main","table":"AKK_CURRENCY","embeddable":false,"persistentEntity":true,"replaceParent":false,"systemLevel":false,"namePattern":"%s|code","mappedSuperclass":false,"fqn":"akkount.entity.Currency","parentPackage":"com.haulmont.cuba.core.entity","parentClassName":"StandardEntity","idAttributeName":"id","attributes":[{"name":"code","type":{"packageName":"java.lang","className":"String","fqn":"java.lang.String","label":"String"},"mappingType":"DATATYPE","readOnly":false,"column":"CODE","mandatory":true,"unique":false,"length":"3","transient":false},{"name":"name","type":{"packageName":"java.lang","className":"String","fqn":"java.lang.String","label":"String"},"mappingType":"DATATYPE","readOnly":false,"column":"NAME","mandatory":false,"unique":false,"length":"50","transient":false}]},{"name":"akk_Operation","className":"Operation","packageName":"akkount.entity","dataStore":"main","table":"AKK_OPERATION","embeddable":false,"persistentEntity":true,"replaceParent":false,"systemLevel":false,"mappedSuperclass":false,"fqn":"akkount.entity.Operation","parentPackage":"com.haulmont.cuba.core.entity","parentClassName":"StandardEntity","idAttributeName":"id","attributes":[{"name":"opType","type":{"packageName":"akkount.entity","className":"OperationType","fqn":"akkount.entity.OperationType","label":"OperationType"},"mappingType":"ENUM","readOnly":false,"column":"OP_TYPE","mandatory":true,"unique":false,"length":"255","transient":false},{"name":"opDate","type":{"packageName":"java.util","className":"Date","fqn":"java.util.Date","label":"Date"},"mappingType":"DATATYPE","readOnly":false,"column":"OP_DATE","mandatory":true,"unique":false,"length":"255","transient":false,"temporalType":"DATE"},{"name":"acc1","type":{"packageName":"akkount.entity","className":"Account","fqn":"akkount.entity.Account","label":"Account","entityName":"akk_Account"},"mappingType":"ASSOCIATION","cardinality":"MANY_TO_ONE","readOnly":false,"column":"ACC1_ID","mandatory":false,"unique":false,"length":"255","transient":false},{"name":"acc2","type":{"packageName":"akkount.entity","className":"Account","fqn":"akkount.entity.Account","label":"Account","entityName":"akk_Account"},"mappingType":"ASSOCIATION","cardinality":"MANY_TO_ONE","readOnly":false,"column":"ACC2_ID","mandatory":false,"unique":false,"length":"255","transient":false},{"name":"amount1","type":{"packageName":"java.math","className":"BigDecimal","fqn":"java.math.BigDecimal","label":"BigDecimal"},"mappingType":"DATATYPE","readOnly":false,"column":"AMOUNT1","mandatory":false,"unique":false,"length":"255","transient":false},{"name":"amount2","type":{"packageName":"java.math","className":"BigDecimal","fqn":"java.math.BigDecimal","label":"BigDecimal"},"mappingType":"DATATYPE","readOnly":false,"column":"AMOUNT2","mandatory":false,"unique":false,"length":"255","transient":false},{"name":"category","type":{"packageName":"akkount.entity","className":"Category","fqn":"akkount.entity.Category","label":"Category","entityName":"akk_Category"},"mappingType":"ASSOCIATION","cardinality":"MANY_TO_ONE","readOnly":false,"column":"CATEGORY_ID","mandatory":false,"unique":false,"length":"255","transient":false},{"name":"comments","type":{"packageName":"java.lang","className":"String","fqn":"java.lang.String","label":"String"},"mappingType":"DATATYPE","readOnly":false,"column":"COMMENTS","mandatory":false,"unique":false,"length":"200","transient":false}]},{"name":"akk_User","className":"User","packageName":"akkount.entity","dataStore":"main","table":"SEC_USER","embeddable":false,"persistentEntity":true,"replaceParent":false,"systemLevel":false,"mappedSuperclass":false,"fqn":"akkount.entity.User","idAttributeName":"id","attributes":[{"name":"id","type":{"packageName":"java.util","className":"UUID","fqn":"java.util.UUID","label":"UUID"},"mappingType":"DATATYPE","readOnly":false,"column":"ID","mandatory":true,"unique":false,"length":"255","transient":false},{"name":"version","type":{"packageName":"java.lang","className":"Integer","fqn":"java.lang.Integer","label":"Integer"},"mappingType":"DATATYPE","readOnly":false,"column":"VERSION","mandatory":true,"unique":false,"length":"255","transient":false},{"name":"username","type":{"packageName":"java.lang","className":"String","fqn":"java.lang.String","label":"String"},"mappingType":"DATATYPE","readOnly":false,"column":"USERNAME","mandatory":true,"unique":false,"length":"255","transient":false},{"name":"password","type":{"packageName":"java.lang","className":"String","fqn":"java.lang.String","label":"String"},"mappingType":"DATATYPE","readOnly":false,"column":"PASSWORD","mandatory":false,"unique":false,"length":"255","transient":false},{"name":"firstName","type":{"packageName":"java.lang","className":"String","fqn":"java.lang.String","label":"String"},"mappingType":"DATATYPE","readOnly":false,"column":"FIRST_NAME","mandatory":false,"unique":false,"length":"255","transient":false},{"name":"lastName","type":{"packageName":"java.lang","className":"String","fqn":"java.lang.String","label":"String"},"mappingType":"DATATYPE","readOnly":false,"column":"LAST_NAME","mandatory":false,"unique":false,"length":"255","transient":false},{"name":"email","type":{"packageName":"java.lang","className":"String","fqn":"java.lang.String","label":"String"},"mappingType":"DATATYPE","readOnly":false,"column":"EMAIL","mandatory":false,"unique":false,"length":"255","transient":false},{"name":"enabled","type":{"packageName":"java.lang","className":"Boolean","fqn":"java.lang.Boolean","label":"Boolean"},"mappingType":"DATATYPE","readOnly":false,"column":"ENABLED","mandatory":false,"unique":false,"length":"255","transient":false},{"name":"authorities","type":{"packageName":"java.util.Collection<? extends org.springframework.security.core","className":"GrantedAuthority>","fqn":"java.util.Collection<? extends org.springframework.security.core.GrantedAuthority>","label":"GrantedAuthority>"},"cardinality":"ONE_TO_MANY","readOnly":false,"mandatory":false,"unique":false,"transient":true}]},{"name":"akk_UserData","className":"UserData","packageName":"akkount.entity","dataStore":"main","table":"AKK_USER_DATA","embeddable":false,"persistentEntity":true,"replaceParent":false,"systemLevel":false,"mappedSuperclass":false,"fqn":"akkount.entity.UserData","parentPackage":"com.haulmont.cuba.core.entity","parentClassName":"BaseUuidEntity","idAttributeName":"id","attributes":[{"name":"user","type":{"packageName":"akkount.entity","className":"User","fqn":"akkount.entity.User","label":"User","entityName":"akk_User"},"mappingType":"ASSOCIATION","cardinality":"MANY_TO_ONE","readOnly":false,"column":"USER_ID","mandatory":true,"unique":false,"length":"255","transient":false},{"name":"key","type":{"packageName":"java.lang","className":"String","fqn":"java.lang.String","label":"String"},"mappingType":"DATATYPE","readOnly":false,"column":"KEY_","mandatory":true,"unique":false,"length":"50","transient":false},{"name":"value","type":{"packageName":"java.lang","className":"String","fqn":"java.lang.String","label":"String"},"mappingType":"DATATYPE","readOnly":false,"column":"VALUE_","mandatory":false,"unique":false,"length":"500","transient":false},{"name":"createTs","type":{"packageName":"java.util","className":"Date","fqn":"java.util.Date","label":"Date"},"mappingType":"DATATYPE","readOnly":false,"column":"CREATE_TS","mandatory":false,"unique":false,"length":"255","transient":false},{"name":"createdBy","type":{"packageName":"java.lang","className":"String","fqn":"java.lang.String","label":"String"},"mappingType":"DATATYPE","readOnly":false,"column":"CREATED_BY","mandatory":false,"unique":false,"length":"50","transient":false}]}],"enums":[{"className":"CategoryType","packageName":"akkount.entity","fqn":"akkount.entity.CategoryType","type":"String","values":[{"name":"EXPENSE","id":"E"},{"name":"INCOME","id":"I"}]},{"className":"OperationType","packageName":"akkount.entity","fqn":"akkount.entity.OperationType","type":"String","values":[{"name":"EXPENSE","id":"E"},{"name":"INCOME","id":"I"},{"name":"TRANSFER","id":"T"}]}],"baseProjectEntities":[],"views":[{"name":"_base","entity":"akk_Account","classFqn":"akkount.entity.Account","overwrite":false,"systemProperties":false,"properties":[{"name":"name","lazy":false},{"name":"description","lazy":false},{"name":"currencyCode","lazy":false},{"name":"active","lazy":false},{"name":"group","lazy":false},{"name":"version","lazy":false},{"name":"createTs","lazy":false},{"name":"createdBy","lazy":false},{"name":"updateTs","lazy":false},{"name":"updatedBy","lazy":false},{"name":"deleteTs","lazy":false},{"name":"deletedBy","lazy":false}],"allProperties":[{"name":"name","lazy":false},{"name":"description","lazy":false},{"name":"currencyCode","lazy":false},{"name":"active","lazy":false},{"name":"group","lazy":false},{"name":"version","lazy":false},{"name":"createTs","lazy":false},{"name":"createdBy","lazy":false},{"name":"updateTs","lazy":false},{"name":"updatedBy","lazy":false},{"name":"deleteTs","lazy":false},{"name":"deletedBy","lazy":false}]},{"name":"_instance_name","entity":"akk_Account","classFqn":"akkount.entity.Account","overwrite":false,"systemProperties":false,"properties":[],"allProperties":[]},{"name":"_local","entity":"akk_Account","classFqn":"akkount.entity.Account","overwrite":false,"systemProperties":false,"properties":[{"name":"name","lazy":false},{"name":"description","lazy":false},{"name":"currencyCode","lazy":false},{"name":"active","lazy":false},{"name":"group","lazy":false},{"name":"version","lazy":false},{"name":"createTs","lazy":false},{"name":"createdBy","lazy":false},{"name":"updateTs","lazy":false},{"name":"updatedBy","lazy":false},{"name":"deleteTs","lazy":false},{"name":"deletedBy","lazy":false}],"allProperties":[{"name":"name","lazy":false},{"name":"description","lazy":false},{"name":"currencyCode","lazy":false},{"name":"active","lazy":false},{"name":"group","lazy":false},{"name":"version","lazy":false},{"name":"createTs","lazy":false},{"name":"createdBy","lazy":false},{"name":"updateTs","lazy":false},{"name":"updatedBy","lazy":false},{"name":"deleteTs","lazy":false},{"name":"deletedBy","lazy":false}]},{"name":"account-with-currency","entity":"akk_Account","classFqn":"akkount.entity.Account","parentName":"_local","overwrite":false,"systemProperties":false,"properties":[{"name":"currency","entity":"akk_Currency","lazy":false}],"allProperties":[{"name":"name","lazy":false},{"name":"description","lazy":false},{"name":"currencyCode","lazy":false},{"name":"active","lazy":false},{"name":"group","lazy":false},{"name":"version","lazy":false},{"name":"createTs","lazy":false},{"name":"createdBy","lazy":false},{"name":"updateTs","lazy":false},{"name":"updatedBy","lazy":false},{"name":"deleteTs","lazy":false},{"name":"deletedBy","lazy":false},{"name":"currency","entity":"akk_Currency","lazy":false}]},{"name":"_base","entity":"akk_Balance","classFqn":"akkount.entity.Balance","overwrite":false,"systemProperties":false,"properties":[{"name":"balanceDate","lazy":false},{"name":"amount","lazy":false},{"name":"version","lazy":false},{"name":"createTs","lazy":false},{"name":"createdBy","lazy":false},{"name":"updateTs","lazy":false},{"name":"updatedBy","lazy":false},{"name":"deleteTs","lazy":false},{"name":"deletedBy","lazy":false}],"allProperties":[{"name":"balanceDate","lazy":false},{"name":"amount","lazy":false},{"name":"version","lazy":false},{"name":"createTs","lazy":false},{"name":"createdBy","lazy":false},{"name":"updateTs","lazy":false},{"name":"updatedBy","lazy":false},{"name":"deleteTs","lazy":false},{"name":"deletedBy","lazy":false}]},{"name":"_instance_name","entity":"akk_Balance","classFqn":"akkount.entity.Balance","overwrite":false,"systemProperties":false,"properties":[],"allProperties":[]},{"name":"_local","entity":"akk_Balance","classFqn":"akkount.entity.Balance","overwrite":false,"systemProperties":false,"properties":[{"name":"balanceDate","lazy":false},{"name":"amount","lazy":false},{"name":"version","lazy":false},{"name":"createTs","lazy":false},{"name":"createdBy","lazy":false},{"name":"updateTs","lazy":false},{"name":"updatedBy","lazy":false},{"name":"deleteTs","lazy":false},{"name":"deletedBy","lazy":false}],"allProperties":[{"name":"balanceDate","lazy":false},{"name":"amount","lazy":false},{"name":"version","lazy":false},{"name":"createTs","lazy":false},{"name":"createdBy","lazy":false},{"name":"updateTs","lazy":false},{"name":"updatedBy","lazy":false},{"name":"deleteTs","lazy":false},{"name":"deletedBy","lazy":false}]},{"name":"_base","entity":"akk_Category","classFqn":"akkount.entity.Category","overwrite":false,"systemProperties":false,"properties":[{"name":"name","lazy":false},{"name":"description","lazy":false},{"name":"catType","lazy":false},{"name":"version","lazy":false},{"name":"createTs","lazy":false},{"name":"createdBy","lazy":false},{"name":"updateTs","lazy":false},{"name":"updatedBy","lazy":false},{"name":"deleteTs","lazy":false},{"name":"deletedBy","lazy":false}],"allProperties":[{"name":"name","lazy":false},{"name":"description","lazy":false},{"name":"catType","lazy":false},{"name":"version","lazy":false},{"name":"createTs","lazy":false},{"name":"createdBy","lazy":false},{"name":"updateTs","lazy":false},{"name":"updatedBy","lazy":false},{"name":"deleteTs","lazy":false},{"name":"deletedBy","lazy":false}]},{"name":"_instance_name","entity":"akk_Category","classFqn":"akkount.entity.Category","overwrite":false,"systemProperties":false,"properties":[],"allProperties":[]},{"name":"_local","entity":"akk_Category","classFqn":"akkount.entity.Category","overwrite":false,"systemProperties":false,"properties":[{"name":"name","lazy":false},{"name":"description","lazy":false},{"name":"catType","lazy":false},{"name":"version","lazy":false},{"name":"createTs","lazy":false},{"name":"createdBy","lazy":false},{"name":"updateTs","lazy":false},{"name":"updatedBy","lazy":false},{"name":"deleteTs","lazy":false},{"name":"deletedBy","lazy":false}],"allProperties":[{"name":"name","lazy":false},{"name":"description","lazy":false},{"name":"catType","lazy":false},{"name":"version","lazy":false},{"name":"createTs","lazy":false},{"name":"createdBy","lazy":false},{"name":"updateTs","lazy":false},{"name":"updatedBy","lazy":false},{"name":"deleteTs","lazy":false},{"name":"deletedBy","lazy":false}]},{"name":"_base","entity":"akk_CategoryBalance","classFqn":"akkount.entity.CategoryAmount","overwrite":false,"systemProperties":false,"properties":[],"allProperties":[]},{"name":"_instance_name","entity":"akk_CategoryBalance","classFqn":"akkount.entity.CategoryAmount","overwrite":false,"systemProperties":false,"properties":[],"allProperties":[]},{"name":"_local","entity":"akk_CategoryBalance","classFqn":"akkount.entity.CategoryAmount","overwrite":false,"systemProperties":false,"properties":[],"allProperties":[]},{"name":"_base","entity":"akk_Currency","classFqn":"akkount.entity.Currency","overwrite":false,"systemProperties":false,"properties":[{"name":"code","lazy":false},{"name":"name","lazy":false},{"name":"version","lazy":false},{"name":"createTs","lazy":false},{"name":"createdBy","lazy":false},{"name":"updateTs","lazy":false},{"name":"updatedBy","lazy":false},{"name":"deleteTs","lazy":false},{"name":"deletedBy","lazy":false}],"allProperties":[{"name":"code","lazy":false},{"name":"name","lazy":false},{"name":"version","lazy":false},{"name":"createTs","lazy":false},{"name":"createdBy","lazy":false},{"name":"updateTs","lazy":false},{"name":"updatedBy","lazy":false},{"name":"deleteTs","lazy":false},{"name":"deletedBy","lazy":false}]},{"name":"_instance_name","entity":"akk_Currency","classFqn":"akkount.entity.Currency","overwrite":false,"systemProperties":false,"properties":[],"allProperties":[]},{"name":"_local","entity":"akk_Currency","classFqn":"akkount.entity.Currency","overwrite":false,"systemProperties":false,"properties":[{"name":"code","lazy":false},{"name":"name","lazy":false},{"name":"version","lazy":false},{"name":"createTs","lazy":false},{"name":"createdBy","lazy":false},{"name":"updateTs","lazy":false},{"name":"updatedBy","lazy":false},{"name":"deleteTs","lazy":false},{"name":"deletedBy","lazy":false}],"allProperties":[{"name":"code","lazy":false},{"name":"name","lazy":false},{"name":"version","lazy":false},{"name":"createTs","lazy":false},{"name":"createdBy","lazy":false},{"name":"updateTs","lazy":false},{"name":"updatedBy","lazy":false},{"name":"deleteTs","lazy":false},{"name":"deletedBy","lazy":false}]},{"name":"_base","entity":"akk_Operation","classFqn":"akkount.entity.Operation","overwrite":false,"systemProperties":false,"properties":[{"name":"opType","lazy":false},{"name":"opDate","lazy":false},{"name":"amount1","lazy":false},{"name":"amount2","lazy":false},{"name":"comments","lazy":false},{"name":"version","lazy":false},{"name":"createTs","lazy":false},{"name":"createdBy","lazy":false},{"name":"updateTs","lazy":false},{"name":"updatedBy","lazy":false},{"name":"deleteTs","lazy":false},{"name":"deletedBy","lazy":false}],"allProperties":[{"name":"opType","lazy":false},{"name":"opDate","lazy":false},{"name":"amount1","lazy":false},{"name":"amount2","lazy":false},{"name":"comments","lazy":false},{"name":"version","lazy":false},{"name":"createTs","lazy":false},{"name":"createdBy","lazy":false},{"name":"updateTs","lazy":false},{"name":"updatedBy","lazy":false},{"name":"deleteTs","lazy":false},{"name":"deletedBy","lazy":false}]},{"name":"_instance_name","entity":"akk_Operation","classFqn":"akkount.entity.Operation","overwrite":false,"systemProperties":false,"properties":[],"allProperties":[]},{"name":"_local","entity":"akk_Operation","classFqn":"akkount.entity.Operation","overwrite":false,"systemProperties":false,"properties":[{"name":"opType","lazy":false},{"name":"opDate","lazy":false},{"name":"amount1","lazy":false},{"name":"amount2","lazy":false},{"name":"comments","lazy":false},{"name":"version","lazy":false},{"name":"createTs","lazy":false},{"name":"createdBy","lazy":false},{"name":"updateTs","lazy":false},{"name":"updatedBy","lazy":false},{"name":"deleteTs","lazy":false},{"name":"deletedBy","lazy":false}],"allProperties":[{"name":"opType","lazy":false},{"name":"opDate","lazy":false},{"name":"amount1","lazy":false},{"name":"amount2","lazy":false},{"name":"comments","lazy":false},{"name":"version","lazy":false},{"name":"createTs","lazy":false},{"name":"createdBy","lazy":false},{"name":"updateTs","lazy":false},{"name":"updatedBy","lazy":false},{"name":"deleteTs","lazy":false},{"name":"deletedBy","lazy":false}]},{"name":"operation-browse","entity":"akk_Operation","classFqn":"akkount.entity.Operation","parentName":"_local","overwrite":false,"systemProperties":true,"properties":[{"name":"acc1","entity":"akk_Account","lazy":false},{"name":"acc2","entity":"akk_Account","lazy":false},{"name":"category","entity":"akk_Category","lazy":false}],"allProperties":[{"name":"opType","lazy":false},{"name":"opDate","lazy":false},{"name":"amount1","lazy":false},{"name":"amount2","lazy":false},{"name":"comments","lazy":false},{"name":"version","lazy":false},{"name":"createTs","lazy":false},{"name":"createdBy","lazy":false},{"name":"updateTs","lazy":false},{"name":"updatedBy","lazy":false},{"name":"deleteTs","lazy":false},{"name":"deletedBy","lazy":false},{"name":"acc1","entity":"akk_Account","lazy":false},{"name":"acc2","entity":"akk_Account","lazy":false},{"name":"category","entity":"akk_Category","lazy":false}]},{"name":"operation-edit","entity":"akk_Operation","classFqn":"akkount.entity.Operation","parentName":"_local","overwrite":false,"systemProperties":false,"properties":[{"name":"acc1","entity":"akk_Account","lazy":false},{"name":"acc2","entity":"akk_Account","lazy":false},{"name":"category","entity":"akk_Category","lazy":false}],"allProperties":[{"name":"opType","lazy":false},{"name":"opDate","lazy":false},{"name":"amount1","lazy":false},{"name":"amount2","lazy":false},{"name":"comments","lazy":false},{"name":"version","lazy":false},{"name":"createTs","lazy":false},{"name":"createdBy","lazy":false},{"name":"updateTs","lazy":false},{"name":"updatedBy","lazy":false},{"name":"deleteTs","lazy":false},{"name":"deletedBy","lazy":false},{"name":"acc1","entity":"akk_Account","lazy":false},{"name":"acc2","entity":"akk_Account","lazy":false},{"name":"category","entity":"akk_Category","lazy":false}]},{"name":"operation-recalc-balance","entity":"akk_Operation","classFqn":"akkount.entity.Operation","overwrite":false,"systemProperties":false,"properties":[{"name":"opDate","lazy":false},{"name":"acc1","entity":"akk_Account","lazy":false},{"name":"acc2","entity":"akk_Account","lazy":false},{"name":"amount1","lazy":false},{"name":"amount2","lazy":false}],"allProperties":[{"name":"opDate","lazy":false},{"name":"acc1","entity":"akk_Account","lazy":false},{"name":"acc2","entity":"akk_Account","lazy":false},{"name":"amount1","lazy":false},{"name":"amount2","lazy":false}]},{"name":"_base","entity":"akk_User","classFqn":"akkount.entity.User","overwrite":false,"systemProperties":false,"properties":[{"name":"firstName","lazy":false},{"name":"lastName","lazy":false},{"name":"username","lazy":false},{"name":"version","lazy":false},{"name":"password","lazy":false},{"name":"email","lazy":false},{"name":"enabled","lazy":false}],"allProperties":[{"name":"firstName","lazy":false},{"name":"lastName","lazy":false},{"name":"username","lazy":false},{"name":"version","lazy":false},{"name":"password","lazy":false},{"name":"email","lazy":false},{"name":"enabled","lazy":false}]},{"name":"_instance_name","entity":"akk_User","classFqn":"akkount.entity.User","overwrite":false,"systemProperties":false,"properties":[{"name":"firstName","lazy":false},{"name":"lastName","lazy":false},{"name":"username","lazy":false}],"allProperties":[{"name":"firstName","lazy":false},{"name":"lastName","lazy":false},{"name":"username","lazy":false}]},{"name":"_local","entity":"akk_User","classFqn":"akkount.entity.User","overwrite":false,"systemProperties":false,"properties":[{"name":"version","lazy":false},{"name":"username","lazy":false},{"name":"password","lazy":false},{"name":"firstName","lazy":false},{"name":"lastName","lazy":false},{"name":"email","lazy":false},{"name":"enabled","lazy":false}],"allProperties":[{"name":"version","lazy":false},{"name":"username","lazy":false},{"name":"password","lazy":false},{"name":"firstName","lazy":false},{"name":"lastName","lazy":false},{"name":"email","lazy":false},{"name":"enabled","lazy":false}]},{"name":"_base","entity":"akk_UserData","classFqn":"akkount.entity.UserData","overwrite":false,"systemProperties":false,"properties":[{"name":"key","lazy":false},{"name":"value","lazy":false},{"name":"createTs","lazy":false},{"name":"createdBy","lazy":false}],"allProperties":[{"name":"key","lazy":false},{"name":"value","lazy":false},{"name":"createTs","lazy":false},{"name":"createdBy","lazy":false}]},{"name":"_instance_name","entity":"akk_UserData","classFqn":"akkount.entity.UserData","overwrite":false,"systemProperties":false,"properties":[],"allProperties":[]},{"name":"_local","entity":"akk_UserData","classFqn":"akkount.entity.UserData","overwrite":false,"systemProperties":false,"properties":[{"name":"key","lazy":false},{"name":"value","lazy":false},{"name":"createTs","lazy":false},{"name":"createdBy","lazy":false}],"allProperties":[{"name":"key","lazy":false},{"name":"value","lazy":false},{"name":"createTs","lazy":false},{"name":"createdBy","lazy":false}]}],"restQueries":[],"restServices":[]}